imgsim/__init__.py
imgsim/imgsim.py
imgsim/model.pth
imgsim-0.1.2.dist-info/LICENSE
imgsim-0.1.2.dist-info/METADATA
imgsim-0.1.2.dist-info/WHEEL
imgsim-0.1.2.dist-info/top_level.txt
imgsim-0.1.2.dist-info/RECORD
